pylint.rc
setup.py
Dovetail.egg-info/PKG-INFO
Dovetail.egg-info/SOURCES.txt
Dovetail.egg-info/dependency_links.txt
Dovetail.egg-info/entry_points.txt
Dovetail.egg-info/requires.txt
Dovetail.egg-info/top_level.txt
dovetail/LICENSE.txt
dovetail/NOTICE.txt
dovetail/USAGE.rst
dovetail/WARRANTY.txt
dovetail/__init__.py
dovetail/config.py
dovetail/constants.py
dovetail/engine.py
dovetail/loader.py
dovetail/main.py
dovetail/model.py
dovetail/test_config.py
dovetail/virtual.py
dovetail/directives/__init__.py
dovetail/directives/core.py
dovetail/directives/engine.py
dovetail/directives/environment.py
dovetail/directives/files.py
dovetail/directives/packages.py
dovetail/directives/test_environment.py
dovetail/directives/test_files.py
dovetail/directives/test_packages.py
dovetail/directives/test_predicates.py
dovetail/util/__init__.py
dovetail/util/exception.py
dovetail/util/logging.py
dovetail/util/test_utilities.py
dovetail/util/trim.py
dovetail/util/utilities.py
dovetail/util/which.py