Metadata-Version: 1.0
Name: Dovetail
Version: 1.0beta3
Summary: A light-weight, multi-platform, build tool for Python with     Continuous Integration servers like Jenkins in mind.
Home-page: http://www.aviser.asia/dovetail
Author: Andrew Alcock, Aviser LLP, Singapore
Author-email: dovetail@aviser.asia
License: GPLv3+
Keywords: build,continuous integration,ci
Platform: UNKNOWN
Classifier: License :: OSI Approved :: GNU General Public License v3 or later (GPLv3+)
Classifier: Programming Language :: Python
Classifier: Programming Language :: Python :: 2.7
Classifier: Development Status :: 4 - Beta
Classifier: Intended Audience :: Developers
Classifier: Topic :: Software Development :: Build Tools
